libgraphfl.so
pygfl/__init__.py
pygfl/bayes.py
pygfl/density.py
pygfl/easy.py
pygfl/solver.py
pygfl/trails.py
pygfl/trendfiltering.py
pygfl/utils.py
pygfl-1.0.2.dist-info/DESCRIPTION.rst
pygfl-1.0.2.dist-info/METADATA
pygfl-1.0.2.dist-info/RECORD
pygfl-1.0.2.dist-info/WHEEL
pygfl-1.0.2.dist-info/entry_points.txt
pygfl-1.0.2.dist-info/metadata.json
pygfl-1.0.2.dist-info/top_level.txt
