Metadata-Version: 2.0
Name: pygfl
Version: 1.0.2
Summary: A Fast and Flexible Graph-Fused Lasso Solver
Home-page: https://github.com/tansey/gfl
Author: Wesley Tansey
Author-email: wes.tansey@gmail.com
License: LGPL
Keywords: statistics machinelearning lasso fusedlasso
Platform: UNKNOWN
Classifier: Development Status :: 3 - Alpha
Classifier: Intended Audience :: Science/Research
Classifier: Topic :: Scientific/Engineering
Classifier: License :: OSI Approved :: GNU Lesser General Public License v3 or later (LGPLv3+)
Classifier: Programming Language :: Python :: 2
Classifier: Programming Language :: Python :: 2.7
Requires-Dist: networkx
Requires-Dist: numpy
Requires-Dist: scipy
